{
    "id": "critical",
    "name": "크리티컬",
    "shake": 25,
    "particles": [
        {
            "type": "flash",
            "size": 200,
            "color": "#ffffff",
            "life": 80
        },
        {
            "type": "flash",
            "size": 150,
            "color": "#fbbf24",
            "life": 120
        },
        {
            "type": "slash",
            "count": 5,
            "delay": 20,
            "angle": [-60, -30, 0, 30, 60],
            "length": [250, 350],
            "width": 15,
            "color": "#ffffff",
            "glow": "#fbbf24",
            "life": 220
        },
        {
            "type": "slash",
            "count": 5,
            "delay": 20,
            "angle": [-60, -30, 0, 30, 60],
            "length": [200, 280],
            "width": 35,
            "color": "rgba(251, 191, 36, 0.6)",
            "glow": "#f59e0b",
            "life": 150
        },
        {
            "type": "ring",
            "size": 40,
            "maxSize": 250,
            "color": "#fbbf24",
            "life": 300
        },
        {
            "type": "ring",
            "size": 30,
            "maxSize": 180,
            "color": "#ffffff",
            "life": 250
        },
        {
            "type": "line",
            "count": 24,
            "angleStep": 15,
            "length": [80, 160],
            "width": 5,
            "color": "#fbbf24",
            "life": 250
        },
        {
            "type": "spark",
            "count": 50,
            "spread": 150,
            "speed": [15, 35],
            "size": [5, 15],
            "colors": ["#fbbf24", "#ffffff", "#f59e0b", "#fcd34d"],
            "life": [300, 600]
        },
        {
            "type": "debris",
            "count": 35,
            "speed": [12, 30],
            "size": [5, 15],
            "colors": ["#fbbf24", "#ef4444", "#f59e0b"],
            "gravity": 0.5,
            "life": [500, 800]
        }
    ]
}
